anitrack/__init__.py
anitrack/track.py
anitrack-0.0.1.dist-info/METADATA
anitrack-0.0.1.dist-info/WHEEL
anitrack-0.0.1.dist-info/top_level.txt
anitrack-0.0.1.dist-info/RECORD
