Metadata-Version: 2.1
Name: anitrack
Version: 0.0.1
Summary: Anime Tracker package.
Home-page: UNKNOWN
Author: mqchinee
License: UNKNOWN
Keywords: python,anime,track
Platform: UNKNOWN
Classifier: Development Status :: 1 - Planning
Classifier: Intended Audience :: Developers
Classifier: Programming Language :: Python :: 3
Classifier: Operating System :: Unix
Classifier: Operating System :: MacOS :: MacOS X
Classifier: Operating System :: Microsoft :: Windows
Requires-Dist: requests
Requires-Dist: bs4
Requires-Dist: urllib3
Requires-Dist: deep-translator
Requires-Dist: argparse
